sprintalizer/__init__.py
sprintalizer/plotter.py
sprintalizer/webserver.py
wattalizer/__init__.py
wattalizer/plotter.py
wattalizer/webserver.py
wattalizer-0.0.1.dist-info/LICENSE
wattalizer-0.0.1.dist-info/METADATA
wattalizer-0.0.1.dist-info/WHEEL
wattalizer-0.0.1.dist-info/top_level.txt
wattalizer-0.0.1.dist-info/RECORD
