Metadata-Version: 2.1
Name: wattalizer
Version: 0.0.1
Summary: Plot GoldenCheetah data for sprint cyclists
Home-page: https://github.com/svenaron/wattalizer
Author: Sven Westergren
Author-email: sven.westergren@gmail.com
License: UNKNOWN
Platform: UNKNOWN
Classifier: Programming Language :: Python :: 3
Classifier: License :: OSI Approved :: MIT License
Classifier: Operating System :: OS Independent
Requires-Python: >=3.6
Requires-Dist: pandas
Requires-Dist: plotly
Requires-Dist: numpy
Requires-Dist: bottle
